Metadata-Version: 1.0
Name: pp-ocr
Version: 1.2
Summary: paddleocr识别
Home-page: UNKNOWN
Author: xdg
Author-email: UNKNOWN
License: Apache Software License
Platform: UNKNOWN
